functional_notations/__init__.py
functional_notations/functional_notations.py
functional_notations/test_functional_notations.py
functional_notations-0.5.1.dist-info/METADATA
functional_notations-0.5.1.dist-info/WHEEL
functional_notations-0.5.1.dist-info/top_level.txt
functional_notations-0.5.1.dist-info/RECORD
